geokernels/__init__.py
geokernels/geodesics.py
geokernels/kernels.py
geokernels/test.py
geokernels/test_geodesics.py
geokernels/test_kernels.py
sklearn_geokernels/__init__.py
sklearn_geokernels/geodesics.py
sklearn_geokernels/kernels.py
sklearn_geokernels/test.py
tests/test_geodesics.py
tests/test_kernel_old.py
tests/test_kernels.py
tests/test_kernels_old.py
geokernels-0.1.3.dist-info/LICENSE
geokernels-0.1.3.dist-info/METADATA
geokernels-0.1.3.dist-info/WHEEL
geokernels-0.1.3.dist-info/top_level.txt
geokernels-0.1.3.dist-info/RECORD
