Metadata-Version: 2.1
Name: geokernels
Version: 0.1.3
Summary: Geodesic Gaussian Process kernels for scikit-learn
Home-page: https://github.com/sigmaterra/geokernels
Author: Sebastian Haan
Author-email: sebhaan@sigmaterra.com
License: MIT
Classifier: Programming Language :: Python :: 3
Classifier: Operating System :: OS Independent
Requires-Python: >=3.8
License-File: LICENSE
Requires-Dist: scikit-learn (>=1.0)
Requires-Dist: numba (>=0.53)
